main.py
logic/core.py
logic/interact.py
logic/model.py
jdolabs_server-0.0.1.dist-info/METADATA
jdolabs_server-0.0.1.dist-info/WHEEL
jdolabs_server-0.0.1.dist-info/entry_points.txt
jdolabs_server-0.0.1.dist-info/top_level.txt
jdolabs_server-0.0.1.dist-info/RECORD
