Metadata-Version: 2.4
Name: jdolabs-server
Version: 0.0.1
Summary: Local AI server with model loading, REST API, and multi-format LLM support
Author: jdolabs
License: MIT
Requires-Dist: fastapi
Requires-Dist: uvicorn
Requires-Dist: transformers
Requires-Dist: safetensors
Requires-Dist: torch
Dynamic: author
Dynamic: license
Dynamic: requires-dist
Dynamic: summary
